pandas_render/__init__.py
pandas_render/py.typed
pandas_render/utils.py
pandas_render/base/Component.py
pandas_render/base/Element.py
pandas_render/base/__init__.py
pandas_render/cli/__init__.py
pandas_render/cli/__main__.py
pandas_render/components/Toggle.py
pandas_render/components/__init__.py
pandas_render/elements/Image.py
pandas_render/elements/Link.py
pandas_render/elements/__init__.py
pandas_render/extensions/DataFrame.py
pandas_render/extensions/Series.py
pandas_render/extensions/__init__.py
pandas_render-0.4.0.dist-info/METADATA
pandas_render-0.4.0.dist-info/WHEEL
pandas_render-0.4.0.dist-info/entry_points.txt
pandas_render-0.4.0.dist-info/licenses/LICENSE
pandas_render-0.4.0.dist-info/RECORD
