Metadata-Version: 2.4
Name: pandas-render
Version: 0.4.0
Summary: A pandas extension for rendering DataFrames
Project-URL: Repository, https://github.com/nok/pandas-render
Project-URL: Issues, https://github.com/nok/pandas-render/issues
Author-email: Darius Morawiec <nok@users.noreply.github.com>
License-Expression: BSD-3-Clause
License-File: LICENSE
Classifier: Programming Language :: Python
Classifier: Programming Language :: Python :: 3
Classifier: Topic :: Scientific/Engineering :: Visualization
Requires-Python: >=3.9
Requires-Dist: ipython>=7.11.1
Requires-Dist: jinja2>=3.0.0
Requires-Dist: typer>=0.15.2
Provides-Extra: examples
Requires-Dist: jupyterlab>=4.3.6; extra == 'examples'
Provides-Extra: pandas
Requires-Dist: pandas>=1.0.0; extra == 'pandas'
Provides-Extra: polars
Requires-Dist: polars>=1.0.0; extra == 'polars'
